CHANGES.yaml
LICENSE
MANIFEST.in
Makefile
README.rst
pyplay.py
setup.py
bin/pyplay
package/__init__.py
package/__init__.pyc
package/errors.py
package/errors.pyc
package/info.py
package/info.pyc
package/info.yaml
package/unittest.py
pyplay.egg-info/PKG-INFO
pyplay.egg-info/SOURCES.txt
pyplay.egg-info/dependency_links.txt
pyplay.egg-info/top_level.txt
tests/test_compiled.py