Metadata-Version: 1.0
Name: pyplay
Version: 1.0.3
Summary: Python Interactive Playground
Home-page: http://github.com/ingydotnet/pyplay-py/
Author: Ingy dot Net
Author-email: ingy@ingy.net
License: Simplified BSD License
Platform: UNKNOWN
Classifier: Development Status :: 3 - Alpha
Classifier: Environment :: Console
Classifier: Intended Audience :: Developers
Classifier: License :: OSI Approved :: BSD License
Classifier: Operating System :: POSIX
Classifier: Programming Language :: Python
Classifier: Topic :: Education
Classifier: Topic :: Software Development :: Testing
Classifier: Topic :: System :: Shells
Classifier: Topic :: Utilities
